MANIFEST.in
setup.py
Puddle.egg-info/PKG-INFO
Puddle.egg-info/SOURCES.txt
Puddle.egg-info/dependency_links.txt
Puddle.egg-info/entry_points.txt
Puddle.egg-info/not-zip-safe
Puddle.egg-info/requires.txt
Puddle.egg-info/top_level.txt
puddle/__init__.py
puddle/perspective.py
puddle/plugin.py
puddle/run.py
puddle/welcome_action.py
puddle/welcome_view.py
puddle/image_editor/__init__.py
puddle/image_editor/image_editor.py
puddle/image_editor/image_editor_extension.py
puddle/image_editor/image_editor_plugin.py
puddle/image_editor/images/image.png
puddle/images/python.png
puddle/images/welcome.png
puddle/images/workbench.png
puddle/property_view/__init__.py
puddle/property_view/property_view.py
puddle/property_view/property_view_plugin.py
puddle/property_view/images/table-bsd.png
puddle/property_view/images/table.png
puddle/python_editor/__init__.py
puddle/python_editor/new_file_action.py
puddle/python_editor/new_file_wizard.py
puddle/python_editor/open_file_action.py
puddle/python_editor/python_editor_action_set.py
puddle/python_editor/python_editor_extension.py
puddle/python_editor/python_editor_plugin.py
puddle/python_editor/python_run_action.py
puddle/python_editor/python_workbench_editor.py
puddle/python_editor/images/document.png
puddle/python_editor/images/new.png
puddle/python_editor/images/python.png
puddle/resource/__init__.py
puddle/resource/api.py
puddle/resource/editor.py
puddle/resource/i_resource.py
puddle/resource/i_workspace.py
puddle/resource/qt_tree_viewer.py
puddle/resource/resource_action_set.py
puddle/resource/resource_adapter.py
puddle/resource/resource_browser.py
puddle/resource/resource_editor.py
puddle/resource/resource_plugin.py
puddle/resource/resource_preferences_page.py
puddle/resource/resource_tree_node.py
puddle/resource/resource_tree_view.py
puddle/resource/resource_tree_viewer.py
puddle/resource/resource_view.py
puddle/resource/resource_wizard.py
puddle/resource/resource_wizard_extension.py
puddle/resource/wizard_extension.py
puddle/resource/workspace_launcher.py
puddle/resource/wx_tree_viewer.py
puddle/resource/action/__init__.py
puddle/resource/action/close_action.py
puddle/resource/action/close_all_action.py
puddle/resource/action/common.py
