Metadata-Version: 1.0
Name: Puddle
Version: 0.1.2
Summary: Extensible Python IDE.
Home-page: http://rwl.github.com/puddle
Author: Richard W. Lincoln
Author-email: r.w.lincoln@gmail.com
License: MIT
Platform: UNKNOWN
